datenguidepy/__init__.py
datenguidepy/output_transformer.py
datenguidepy/query_builder.py
datenguidepy/query_execution.py
datenguidepy/query_helper.py
datenguidepy/regions.csv
datenguidepy-0.1.1.dist-info/LICENSE
datenguidepy-0.1.1.dist-info/METADATA
datenguidepy-0.1.1.dist-info/WHEEL
datenguidepy-0.1.1.dist-info/top_level.txt
datenguidepy-0.1.1.dist-info/RECORD
