Metadata-Version: 2.1
Name: datenguidepy
Version: 0.1.1
Summary: Provids easy access to German publically availible regional statistics
Home-page: https://github.com/CorrelAid/datenguide-python
Author: CorrelAid
Author-email: packages@correlaid.org
License: MIT license
Keywords: datenguidepy
Platform: UNKNOWN
Classifier: Development Status :: 4 - Beta
Classifier: Intended Audience :: Developers
Classifier: Intended Audience :: Education
Classifier: Intended Audience :: Other Audience
Classifier: Intended Audience :: Science/Research
Classifier: Natural Language :: English
Classifier: Natural Language :: German
Classifier: Operating System :: OS Independent
Classifier: Topic :: Education
Classifier: Topic :: Sociology
Classifier: License :: OSI Approved :: MIT License
Classifier: Programming Language :: Python :: 3.6
Classifier: Programming Language :: Python :: 3.7
Requires-Dist: pandas
Requires-Dist: requests
